physioqc/__init__.py
physioqc/_version.py
physioqc/due.py
physioqc/references.py
physioqc/workflow.py
physioqc/interfaces/__init__.py
physioqc/interfaces/interfaces.py
physioqc/interfaces/visualizations.py
physioqc/metrics/__init__.py
physioqc/metrics/cardiac.py
physioqc/metrics/chest_belt.py
physioqc/metrics/gas.py
physioqc/metrics/multimodal.py
physioqc/metrics/utils.py
physioqc/tests/__init__.py
physioqc-0.8.2.dist-info/LICENSE
physioqc-0.8.2.dist-info/METADATA
physioqc-0.8.2.dist-info/WHEEL
physioqc-0.8.2.dist-info/entry_points.txt
physioqc-0.8.2.dist-info/top_level.txt
physioqc-0.8.2.dist-info/RECORD
